tests/__init__.py
tests/test_config.py
wikly/__init__.py
wikly/analyzer.py
wikly/api.py
wikly/cli.py
wikly/config.py
wikly/gemini.py
wikly/utils.py
wikly/commands/__init__.py
wikly/commands/analyze.py
wikly/commands/export.py
wikly/commands/init.py
wikly/commands/list_pages.py
wikly/commands/models.py
wikly/commands/report.py
wikly/commands/test.py
wikly/tests/__init__.py
wikly/tests/test_api.py
wikly-0.2.1.dist-info/METADATA
wikly-0.2.1.dist-info/WHEEL
wikly-0.2.1.dist-info/entry_points.txt
wikly-0.2.1.dist-info/top_level.txt
wikly-0.2.1.dist-info/RECORD
