Metadata-Version: 2.2
Name: wikly
Version: 0.2.1
Summary: A tool to export and analyze Wiki.js content with AI capabilities
Home-page: https://github.com/barisgit/wikly
Author: Wikly Contributors
Author-email: baristovnik@gmail.com
Keywords: wiki,wiki.js,export,analyze,ai,style-guide,content-management
Classifier: Development Status :: 4 - Beta
Classifier: Environment :: Console
Classifier: Intended Audience :: Developers
Classifier: Intended Audience :: System Administrators
Classifier: License :: OSI Approved :: MIT License
Classifier: Programming Language :: Python :: 3
Classifier: Programming Language :: Python :: 3.8
Classifier: Programming Language :: Python :: 3.9
Classifier: Programming Language :: Python :: 3.10
Classifier: Programming Language :: Python :: 3.11
Classifier: Programming Language :: Python :: 3.12
Classifier: Programming Language :: Python :: 3.13
Classifier: Topic :: Utilities
Requires-Python: >=3.8
Requires-Dist: requests>=2.25.0
Requires-Dist: click>=8.0.0
Requires-Dist: python-dotenv>=0.15.0
Requires-Dist: pathlib>=1.0.1
Requires-Dist: pyyaml>=6.0.1
Requires-Dist: markdown>=3.7.0
Provides-Extra: dev
Requires-Dist: pytest>=7.0.0; extra == "dev"
Requires-Dist: pytest-mock>=3.10.0; extra == "dev"
Requires-Dist: pytest-cov>=4.0.0; extra == "dev"
Requires-Dist: pytest-asyncio>=0.21.0; extra == "dev"
Dynamic: author
Dynamic: author-email
Dynamic: classifier
Dynamic: description
Dynamic: description-content-type
Dynamic: home-page
Dynamic: keywords
Dynamic: provides-extra
Dynamic: requires-dist
Dynamic: requires-python
Dynamic: summary
